{
    "total": 1,
    "limit": 100,
    "page": null,
    "criteria": {
        "id": "5df1f753487d0f4c498b4883"
    },
    "sort": [],
    "mmobjs": [
        {
            "collection": false,
            "id": "5df1f753487d0f4c498b4883",
            "numericalID": 262,
            "immutable": null,
            "secret": "t2v9q5piiw0ggcg44sswww8wo8ggww0",
            "locale": "es",
            "rank": 13,
            "live": false,
            "type": 1,
            "status": 0,
            "published": true,
            "blocked": false,
            "hidden": false,
            "prototype": false,
            "recordDate": "1990-12-29T09:16:20+01:00",
            "publicDate": "1990-12-29T09:16:20+01:00",
            "title": "Primer plano (1990)",
            "i18nTitle": {
                "es": "Primer plano (1990)"
            },
            "subtitle": "",
            "i18nSubtitle": {
                "es": ""
            },
            "description": "Presentado por Antonio Banderas y Ana Obregón, el programa incluyó un resumen de lo que pasó en el cine español durate el año 1990. ",
            "i18nDescription": {
                "es": "Presentado por Antonio Banderas y Ana Obregón, el programa incluyó un resumen de lo que pasó en el cine español durate el año 1990. "
            },
            "comments": null,
            "line2": "",
            "i18nLine2": {
                "es": ""
            },
            "copyright": "Movistar",
            "license": null,
            "duration": 1723,
            "durationString": "28' 43''",
            "numview": 1,
            "series": {
                "proxyInitializer": null,
                "proxyInitialized": true,
                "collection": true,
                "id": "5df1f728487d0f4c498b4852",
                "numericalID": 13,
                "secret": "oyrcpkjngw04o0owg0k00wow0g40w8w",
                "type": 0,
                "playlist": {
                    "multimediaObjects": [],
                    "publishedMultimediaObjects": [],
                    "publishedAndHiddenMultimediaObjects": [],
                    "multimediaObjectsByStatus": [],
                    "multimediaObjectsIdList": []
                },
                "sorting": 1,
                "sortingCriteria": {
                    "public_date": "asc"
                },
                "seriesType": null,
                "seriesStyle": null,
                "announce": false,
                "hide": false,
                "publicDate": "2019-12-12T09:15:36+01:00",
                "title": "Programas de actualidad",
                "i18nTitle": {
                    "es": "Programas de actualidad"
                },
                "subtitle": "",
                "i18nSubtitle": {
                    "es": ""
                },
                "description": "",
                "comments": null,
                "i18nDescription": {
                    "es": ""
                },
                "header": "",
                "i18nHeader": {
                    "es": ""
                },
                "footer": "",
                "i18nFooter": {
                    "es": ""
                },
                "copyright": null,
                "license": null,
                "line2": "",
                "i18nLine2": {
                    "es": ""
                },
                "locale": "es",
                "textIndex": [
                    {
                        "indexlanguage": "es",
                        "text": "programas de actualidad | "
                    }
                ],
                "secondaryTextIndex": [
                    {
                        "indexlanguage": "es",
                        "text": ""
                    }
                ],
                "i18nKeyword": {
                    "es": ""
                },
                "keywords": [],
                "keywordsAsString": "",
                "i18nKeywords": {
                    "es": []
                },
                "properties": {
                    "owners": [
                        "5d91c5f0487d0f88128b4567",
                        "5d8cdb40487d0fc01a8b45a8"
                    ],
                    "template": "date"
                },
                "videoHead": null,
                "videoTail": null,
                "pics": [],
                "pic": null,
                "firstUrlPic": "",
                "filteredPicsWithTags": []
            },
            "seriesTitle": "Programas de actualidad",
            "embeddedEvent": null,
            "embeddedSegments": [],
            "embeddedBroadcastNotNull": {
                "id": "5df1f753487d0f4c498b4884",
                "name": "Only logged in Users",
                "type": "login",
                "password": null,
                "groups": [],
                "passwordValid": false
            },
            "embeddedBroadcast": {
                "id": "5df1f753487d0f4c498b4884",
                "name": "Only logged in Users",
                "type": "login",
                "password": null,
                "groups": [],
                "passwordValid": false
            },
            "publicEmbeddedBroadcast": false,
            "embeddedSocial": null,
            "tags": [
                {
                    "id": "5df1f53c487d0f8f488b4569",
                    "title": "WebTV",
                    "i18nTitle": {
                        "en": "WebTV",
                        "es": "WebTV"
                    },
                    "description": "",
                    "i18nDescription": {
                        "en": ""
                    },
                    "slug": null,
                    "cod": "PUCHWEBTV",
                    "metatag": false,
                    "display": true,
                    "created": null,
                    "updated": null,
                    "locale": "es",
                    "level": 3,
                    "path": "ROOT|PUBCHANNELS|PUCHWEBTV|",
                    "pubTag": true
                },
                {
                    "id": "5df1f53c487d0f8f488b4568",
                    "title": "PUBCHANNELS",
                    "i18nTitle": {
                        "en": "PUBCHANNELS",
                        "es": "PUBCHANNELS"
                    },
                    "description": "",
                    "i18nDescription": {
                        "en": ""
                    },
                    "slug": null,
                    "cod": "PUBCHANNELS",
                    "metatag": true,
                    "display": false,
                    "created": null,
                    "updated": null,
                    "locale": "es",
                    "level": 2,
                    "path": "ROOT|PUBCHANNELS|",
                    "pubTag": false
                },
                {
                    "id": "5df1f53c487d0f8f488b4567",
                    "title": "ROOT",
                    "i18nTitle": {
                        "en": "ROOT",
                        "es": "ROOT"
                    },
                    "description": "",
                    "i18nDescription": {
                        "en": ""
                    },
                    "slug": null,
                    "cod": "ROOT",
                    "metatag": true,
                    "display": false,
                    "created": null,
                    "updated": null,
                    "locale": "es",
                    "level": 1,
                    "path": "ROOT|",
                    "pubTag": false
                },
                {
                    "id": "5df1f728487d0f4c498b484f",
                    "title": "Programas de actualidad",
                    "i18nTitle": {
                        "en": "",
                        "es": "Programas de actualidad"
                    },
                    "description": "",
                    "i18nDescription": {
                        "en": ""
                    },
                    "slug": null,
                    "cod": "PROGRAMAS_DE_ACTUALIDAD",
                    "metatag": false,
                    "display": true,
                    "created": null,
                    "updated": null,
                    "locale": "es",
                    "level": 3,
                    "path": "ROOT|MOVISTAR|PROGRAMAS_DE_ACTUALIDAD|",
                    "pubTag": false
                },
                {
                    "id": "5df1f53d487d0f97488b4567",
                    "title": "Movistar",
                    "i18nTitle": {
                        "en": "Movistar",
                        "es": "Movistar"
                    },
                    "description": "",
                    "i18nDescription": {
                        "en": ""
                    },
                    "slug": null,
                    "cod": "MOVISTAR",
                    "metatag": true,
                    "display": true,
                    "created": null,
                    "updated": null,
                    "locale": "es",
                    "level": 2,
                    "path": "ROOT|MOVISTAR|",
                    "pubTag": false
                }
            ],
            "tracks": [
                {
                    "language": "es",
                    "acodec": "aac",
                    "originalName": "1810169LB.mp4",
                    "vcodec": "h264",
                    "bitrate": 1425162,
                    "framerate": "25/1",
                    "numFrames": 43075,
                    "onlyAudio": false,
                    "channels": 2,
                    "duration": 1723,
                    "width": 1280,
                    "height": 720,
                    "numview": 1,
                    "allowDownload": false,
                    "resolution": {
                        "width": 1280,
                        "height": 720
                    },
                    "aspectRatio": 1.7777777777777777,
                    "durationInMinutesAndSeconds": {
                        "minutes": 28,
                        "seconds": 43
                    },
                    "master": true,
                    "profileName": "broadcastable_master_copy",
                    "id": "5df1fb8d487d0fd1618b4567",
                    "tags": [
                        "profile:broadcastable_master_copy",
                        "master",
                        "display"
                    ],
                    "url": "https://descarga.videotecamovistarplus.es/downloads/5df1f728487d0f4c498b4852/5df1f755487d0f4c498b4885.mp4",
                    "path": "/mnt/pumukit/storage/movistar-storage/downloads/5df1f728487d0f4c498b4852/5df1f755487d0f4c498b4885.mp4",
                    "mimeType": "video/mp4",
                    "size": 307058486,
                    "hide": false,
                    "description": "",
                    "i18nDescription": {
                        "en": ""
                    },
                    "locale": "es",
                    "properties": []
                }
            ],
            "realDuration": 1723,
            "master": {
                "language": "es",
                "acodec": "aac",
                "originalName": "1810169LB.mp4",
                "vcodec": "h264",
                "bitrate": 1425162,
                "framerate": "25/1",
                "numFrames": 43075,
                "onlyAudio": false,
                "channels": 2,
                "duration": 1723,
                "width": 1280,
                "height": 720,
                "numview": 1,
                "allowDownload": false,
                "resolution": {
                    "width": 1280,
                    "height": 720
                },
                "aspectRatio": 1.7777777777777777,
                "durationInMinutesAndSeconds": {
                    "minutes": 28,
                    "seconds": 43
                },
                "master": true,
                "profileName": "broadcastable_master_copy",
                "id": "5df1fb8d487d0fd1618b4567",
                "tags": [
                    "profile:broadcastable_master_copy",
                    "master",
                    "display"
                ],
                "url": "https://descarga.videotecamovistarplus.es/downloads/5df1f728487d0f4c498b4852/5df1f755487d0f4c498b4885.mp4",
                "path": "/mnt/pumukit/storage/movistar-storage/downloads/5df1f728487d0f4c498b4852/5df1f755487d0f4c498b4885.mp4",
                "mimeType": "video/mp4",
                "size": 307058486,
                "hide": false,
                "description": "",
                "i18nDescription": {
                    "en": ""
                },
                "locale": "es",
                "properties": []
            },
            "displayTrack": {
                "language": "es",
                "acodec": "aac",
                "originalName": "1810169LB.mp4",
                "vcodec": "h264",
                "bitrate": 1425162,
                "framerate": "25/1",
                "numFrames": 43075,
                "onlyAudio": false,
                "channels": 2,
                "duration": 1723,
                "width": 1280,
                "height": 720,
                "numview": 1,
                "allowDownload": false,
                "resolution": {
                    "width": 1280,
                    "height": 720
                },
                "aspectRatio": 1.7777777777777777,
                "durationInMinutesAndSeconds": {
                    "minutes": 28,
                    "seconds": 43
                },
                "master": true,
                "profileName": "broadcastable_master_copy",
                "id": "5df1fb8d487d0fd1618b4567",
                "tags": [
                    "profile:broadcastable_master_copy",
                    "master",
                    "display"
                ],
                "url": "https://descarga.videotecamovistarplus.es/downloads/5df1f728487d0f4c498b4852/5df1f755487d0f4c498b4885.mp4",
                "path": "/mnt/pumukit/storage/movistar-storage/downloads/5df1f728487d0f4c498b4852/5df1f755487d0f4c498b4885.mp4",
                "mimeType": "video/mp4",
                "size": 307058486,
                "hide": false,
                "description": "",
                "i18nDescription": {
                    "en": ""
                },
                "locale": "es",
                "properties": []
            },
            "filteredTracksWithTags": [
                {
                    "language": "es",
                    "acodec": "aac",
                    "originalName": "1810169LB.mp4",
                    "vcodec": "h264",
                    "bitrate": 1425162,
                    "framerate": "25/1",
                    "numFrames": 43075,
                    "onlyAudio": false,
                    "channels": 2,
                    "duration": 1723,
                    "width": 1280,
                    "height": 720,
                    "numview": 1,
                    "allowDownload": false,
                    "resolution": {
                        "width": 1280,
                        "height": 720
                    },
                    "aspectRatio": 1.7777777777777777,
                    "durationInMinutesAndSeconds": {
                        "minutes": 28,
                        "seconds": 43
                    },
                    "master": true,
                    "profileName": "broadcastable_master_copy",
                    "id": "5df1fb8d487d0fd1618b4567",
                    "tags": [
                        "profile:broadcastable_master_copy",
                        "master",
                        "display"
                    ],
                    "url": "https://descarga.videotecamovistarplus.es/downloads/5df1f728487d0f4c498b4852/5df1f755487d0f4c498b4885.mp4",
                    "path": "/mnt/pumukit/storage/movistar-storage/downloads/5df1f728487d0f4c498b4852/5df1f755487d0f4c498b4885.mp4",
                    "mimeType": "video/mp4",
                    "size": 307058486,
                    "hide": false,
                    "description": "",
                    "i18nDescription": {
                        "en": ""
                    },
                    "locale": "es",
                    "properties": []
                }
            ],
            "filteredTrackWithTags": {
                "language": "es",
                "acodec": "aac",
                "originalName": "1810169LB.mp4",
                "vcodec": "h264",
                "bitrate": 1425162,
                "framerate": "25/1",
                "numFrames": 43075,
                "onlyAudio": false,
                "channels": 2,
                "duration": 1723,
                "width": 1280,
                "height": 720,
                "numview": 1,
                "allowDownload": false,
                "resolution": {
                    "width": 1280,
                    "height": 720
                },
                "aspectRatio": 1.7777777777777777,
                "durationInMinutesAndSeconds": {
                    "minutes": 28,
                    "seconds": 43
                },
                "master": true,
                "profileName": "broadcastable_master_copy",
                "id": "5df1fb8d487d0fd1618b4567",
                "tags": [
                    "profile:broadcastable_master_copy",
                    "master",
                    "display"
                ],
                "url": "https://descarga.videotecamovistarplus.es/downloads/5df1f728487d0f4c498b4852/5df1f755487d0f4c498b4885.mp4",
                "path": "/mnt/pumukit/storage/movistar-storage/downloads/5df1f728487d0f4c498b4852/5df1f755487d0f4c498b4885.mp4",
                "mimeType": "video/mp4",
                "size": 307058486,
                "hide": false,
                "description": "",
                "i18nDescription": {
                    "en": ""
                },
                "locale": "es",
                "properties": []
            },
            "people": [],
            "peopleByRole": [],
            "peopleByRoleCod": [],
            "roles": [],
            "groups": [],
            "onlyAudio": false,
            "durationInMinutesAndSeconds": {
                "minutes": 28,
                "seconds": 43
            },
            "multistream": false,
            "textIndex": [
                {
                    "indexlanguage": "es",
                    "text": "primer plano (1990) |  | programas de actualidad"
                }
            ],
            "secondaryTextIndex": [
                {
                    "indexlanguage": "es",
                    "text": "presentado por antonio banderas y ana obregon, el programa incluyo un resumen de lo que paso en el cine espanol durate el ano 1990. "
                }
            ],
            "head": false,
            "tail": false,
            "i18nKeyword": {
                "es": ""
            },
            "keywords": [],
            "keywordsAsString": "",
            "i18nKeywords": {
                "es": []
            },
            "properties": {
                "created": "2019-12-12T09:16:19+01:00",
                "originId": "1810169",
                "finished_jobs": [
                    "5df1f755487d0f4c498b4885"
                ],
                "subseries": false,
                "subseriestitle": {
                    "es": ""
                }
            },
            "videoHead": null,
            "videoTail": null,
            "links": [],
            "filteredLinksWithTags": [],
            "pics": [
                {
                    "width": 304,
                    "height": 171,
                    "time": 861.5,
                    "id": "5df1fb8d487d0fd1618b4568",
                    "tags": [
                        "auto",
                        "frame_21537.5",
                        "time_861.5"
                    ],
                    "url": "/uploads/pic/series/5df1f728487d0f4c498b4852/video/5df1f753487d0f4c498b4883/19121293421.jpg",
                    "path": "/var/www/movistar-prod-pumukit/web/uploads/pic/series/5df1f728487d0f4c498b4852/video/5df1f753487d0f4c498b4883/19121293421.jpg",
                    "mimeType": null,
                    "size": null,
                    "hide": false,
                    "description": "",
                    "i18nDescription": {
                        "en": ""
                    },
                    "locale": "es",
                    "properties": []
                }
            ],
            "pic": {
                "width": 304,
                "height": 171,
                "time": 861.5,
                "id": "5df1fb8d487d0fd1618b4568",
                "tags": [
                    "auto",
                    "frame_21537.5",
                    "time_861.5"
                ],
                "url": "/uploads/pic/series/5df1f728487d0f4c498b4852/video/5df1f753487d0f4c498b4883/19121293421.jpg",
                "path": "/var/www/movistar-prod-pumukit/web/uploads/pic/series/5df1f728487d0f4c498b4852/video/5df1f753487d0f4c498b4883/19121293421.jpg",
                "mimeType": null,
                "size": null,
                "hide": false,
                "description": "",
                "i18nDescription": {
                    "en": ""
                },
                "locale": "es",
                "properties": []
            },
            "firstUrlPic": "/uploads/pic/series/5df1f728487d0f4c498b4852/video/5df1f753487d0f4c498b4883/19121293421.jpg",
            "filteredPicsWithTags": [
                {
                    "width": 304,
                    "height": 171,
                    "time": 861.5,
                    "id": "5df1fb8d487d0fd1618b4568",
                    "tags": [
                        "auto",
                        "frame_21537.5",
                        "time_861.5"
                    ],
                    "url": "/uploads/pic/series/5df1f728487d0f4c498b4852/video/5df1f753487d0f4c498b4883/19121293421.jpg",
                    "path": "/var/www/movistar-prod-pumukit/web/uploads/pic/series/5df1f728487d0f4c498b4852/video/5df1f753487d0f4c498b4883/19121293421.jpg",
                    "mimeType": null,
                    "size": null,
                    "hide": false,
                    "description": "",
                    "i18nDescription": {
                        "en": ""
                    },
                    "locale": "es",
                    "properties": []
                }
            ],
            "materials": [],
            "filteredMaterialsWithTags": []
        }
    ]
}